[
    {
        "pk": 1,
        "model": "mainapp.report",
        "fields": {
            "category": 5,
            "is_hate": false,
            "sent_at": "2011-10-21 04:27:29",
            "is_confirmed": true,
            "title": "Graffiti sur le monument",
            "photo": "photos/photo_12.jpeg",
            "created_at": "2011-10-21 04:26:44",
            "point": "POINT (149683.8125000000000000 171674.4687500000000000)",
            "updated_at": "2011-10-21 04:26:44",
            "email_sent_to": "jsanchezpando@cirb.irisnet.be",
            "author": "Auqui\u00e8re Eric",
            "fixed_at": null,
            "reminded_at": "2011-10-21 04:26:44",
            "postalcode": "1210",
            "ward": 14,
            "is_fixed": false,
            "address": "Rue Botanique, 57",
            "desc": "Grafiti sur la fesse gauche"
        }
    },
    {
        "pk": 2,
        "model": "mainapp.report",
        "fields": {
            "category": 3,
            "is_hate": false,
            "sent_at": "2011-10-18 07:11:40",
            "is_confirmed": true,
            "title": "Ampoule du lampadaire brul\u00e9",
            "photo": "",
            "created_at": "2011-10-18 06:58:36",
            "point": "POINT (150043.6250000000000000 170632.7968750000000000)",
            "updated_at": "2011-10-18 06:58:36",
            "email_sent_to": "jsanchezpandoF@cirb.irisnet.be",
            "author": "Jonathan",
            "fixed_at": null,
            "reminded_at": "2011-10-18 06:58:36",
            "postalcode": "1000",
            "ward": 4,
            "is_fixed": false,
            "address": "Avenue des Arts, 21",
            "desc": "Plusieurs lampadaires sur le c\u00f4t\u00e9 sud de la 3e Avenue entre les rues Bank et O'Connor souffrent d'intermittents \u00e0 l'\u00e9chec permanent."
        }
    },
    {
        "pk": 3,
        "model": "mainapp.report",
        "fields": {
            "category": 9,
            "is_hate": false,
            "sent_at": "2011-10-19 03:02:18",
            "is_confirmed": true,
            "title": "Nids-de-poule et fissures dan les pistes cyclables",
            "photo": "photos/photo_10.jpeg",
            "created_at": "2011-10-19 02:58:40",
            "point": "POINT (148847.8125000000000000 170634.0000000000000000)",
            "updated_at": "2011-10-19 09:01:38",
            "email_sent_to": "jsanchezpando@cirb.irisnet.be",
            "author": "Jonathan",
            "fixed_at": null,
            "reminded_at": "2011-10-19 02:58:40",
            "postalcode": "1000",
            "ward": 4,
            "is_fixed": false,
            "address": "Rue des Brasseurs, 12",
            "desc": "La piste cyclable en direction ouest sur Ogilve d'au moins Park Drive Ville \u00e0 Saint-Laurent a de nombreux nids de poule et des fissures qui pourraient facilement provoquer un accident pour un cycliste. Les nids de poule sont surtout autour des plaques d'\u00e9gout et depuis la piste cyclable est si \u00e9troite, un cycliste doit sortir de la piste pour \u00e9viter de heurter les trous."
        }
    },
    {
        "pk": 4,
        "model": "mainapp.report",
        "fields": {
            "category": 4,
            "is_hate": false,
            "sent_at": "2011-09-11 07:12:02",
            "is_confirmed": true,
            "title": "V\u00e9lo abandonn\u00e9s",
            "photo": "",
            "created_at": "2011-09-11 07:03:20",
            "point": "POINT (149928.1562500000000000 170942.7187500000000000)",
            "updated_at": "2011-10-18 07:03:20",
            "email_sent_to": "jsanchezpandoF@cirb.irisnet.be",
            "author": "Jonathan",
            "fixed_at": null,
            "reminded_at": "2011-10-18 07:03:20",
            "postalcode": "1000",
            "ward": 4,
            "is_fixed": false,
            "address": "Rue de la Croix de Fer, 108",
            "desc": "Il ya un v\u00e9lo apparament d\u00e9cent abandonn\u00e9s ici juste \u00e0 c\u00f4t\u00e9 de la passerelle. Il est l\u00e0 pour quelques jours."
        }
    },
    {
        "pk": 5,
        "model": "mainapp.report",
        "fields": {
            "category": 11,
            "is_hate": false,
            "sent_at": "2011-10-18 08:07:47",
            "is_confirmed": true,
            "title": "Bouteilles de bi\u00e8re cass\u00e9es",
            "photo": "photos/photo_5.jpeg",
            "created_at": "2011-10-18 08:07:33",
            "point": "POINT (151714.0000000000000000 169689.0000000000000000)",
            "updated_at": "2011-10-18 08:07:33",
            "email_sent_to": "jsanchezpando@cirb.irisnet.be",
            "author": "Jonathan",
            "fixed_at": null,
            "reminded_at": "2011-10-18 08:07:33",
            "postalcode": "1040",
            "ward": 5,
            "is_fixed": false,
            "address": "Mont du Cinquantenaire, 3",
            "desc": "Bouteilles de bi\u00e8re cass\u00e9es occupe le sentier et la piste cyclable."
        }
    },
    {
        "pk": 6,
        "model": "mainapp.report",
        "fields": {
            "category": 20,
            "is_hate": false,
            "sent_at": "2011-10-18 07:11:55",
            "is_confirmed": true,
            "title": "Arbustes envahi le trottoir",
            "photo": "",
            "created_at": "2011-10-18 07:01:58",
            "point": "POINT (150649.2656250000000000 171065.0937500000000000)",
            "updated_at": "2011-10-18 07:01:58",
            "email_sent_to": "jsanchezpandoF@cirb.irisnet.be",
            "author": "Jonathan",
            "fixed_at": null,
            "reminded_at": "2011-10-18 07:01:58",
            "postalcode": "1210",
            "ward": 14,
            "is_fixed": false,
            "address": "Rue Braemt, 2",
            "desc": "Les arbustes et les arbres envahissent la piste cyclable / trottoir. De plus en plus difficile pour les marcheurs et les cyclistes."
        }
    },
    {
        "pk": 7,
        "model": "mainapp.report",
        "fields": {
            "category": 19,
            "is_hate": false,
            "sent_at": "2011-10-21 03:31:51",
            "is_confirmed": true,
            "title": "Enseigne CIRB",
            "photo": "",
            "created_at": "2011-10-21 03:30:52",
            "point": "POINT (150079.6562500000000000 170650.7187500000000000)",
            "updated_at": "2011-10-21 03:30:52",
            "email_sent_to": "jsanchezpando@cirb.irisnet.be",
            "author": "Auqui\u00e8re Eric",
            "fixed_at": null,
            "reminded_at": "2011-10-21 03:30:52",
            "postalcode": "1000",
            "ward": 4,
            "is_fixed": false,
            "address": "Rue Joseph II, 5",
            "desc": "Il n'y a pas d'enseigne au CIRB"
        }
    },
    {
        "pk": 8,
        "model": "mainapp.report",
        "fields": {
            "category": 5,
            "is_hate": false,
            "sent_at": "2011-10-18 08:46:43",
            "is_confirmed": true,
            "title": "Graffity sur le mur de l'\u00e9cole",
            "photo": "photos/photo_8.jpeg",
            "created_at": "2011-10-18 08:46:22",
            "point": "POINT (149672.2031250000000000 171027.6875000000000000)",
            "updated_at": "2011-11-02 10:52:08",
            "email_sent_to": "jsanchezpando@cirb.irisnet.be",
            "author": "Jonathan",
            "fixed_at": "2011-10-02 10:52:08",
            "reminded_at": "2011-10-18 08:46:22",
            "postalcode": "1000",
            "ward": 4,
            "is_fixed": true,
            "address": "Rue Royale, 71",
            "desc": "propri\u00e9t\u00e9 de l'\u00e9cole ESI, sur le mur sud. Grandes marques de peinture en a\u00e9rosol rouges \"arabe\". Il y a en beaucoup plus dans le quartier depuis le dimanche matin, a du arriv\u00e9 le samedi soir."
        }
    },
    {
        "pk": 9,
        "model": "mainapp.report",
        "fields": {
            "category": 4,
            "is_hate": false,
            "sent_at": "2011-10-18 09:01:53",
            "is_confirmed": true,
            "title": "Animaux morts dans sac blanc",
            "photo": "photos/photo_9.jpeg",
            "created_at": "2011-10-18 09:01:40",
            "point": "POINT (149822.8125000000000000 171452.3750000000000000)",
            "updated_at": "2011-10-18 09:01:40",
            "email_sent_to": "jsanchezpando@cirb.irisnet.be",
            "author": "Jonathan",
            "fixed_at": null,
            "reminded_at": "2011-10-18 09:01:40",
            "postalcode": "1210",
            "ward": 14,
            "is_fixed": false,
            "address": "Rue Royale, 153",
            "desc": "Je crois qu'il s'agit d'un chat adulte. J'ai appel\u00e9 la SPA, mais ils n'ont pas eu suffisamment de preuves que cela soit criminel. J'ai \u00e9t\u00e9 d\u00e9\u00e7u car il semblerait que quelqu'un a tu\u00e9 cet animal et l'a mis dans un sac poubelle blanc. Voisins curieux ont ouvert le sac partiellement \u00e0 r\u00e9v\u00e9ler les d\u00e9buts de la d\u00e9composition (asticots). Les enfants et les animaux empreintent \u00e0 pied cette passerelle. S'il vous pla\u00eet que quelqu'un viennent se d\u00e9barrasser de ceci, je vous en remercie.\r\nA la pointe la plus au nord du chemin Ogilvie, comme on marche sur la voie vers le fleuve, le sac est \u00e0 c\u00f4t\u00e9 du mur de couverture sur la droite."
        }
    },
    {
        "pk": 10,
        "model": "mainapp.report",
        "fields": {
            "category": 20,
            "is_hate": false,
            "sent_at": "2011-10-18 08:27:27",
            "is_confirmed": true,
            "title": "Arbre tomb\u00e9 \u00e0 travers le passage / piste cyclable",
            "photo": "",
            "created_at": "2011-10-18 08:27:17",
            "point": "POINT (150435.7187500000000000 170406.8125000000000000)",
            "updated_at": "2011-11-02 10:41:05",
            "email_sent_to": "jsanchezpando@cirb.irisnet.be",
            "author": "Jonathan",
            "fixed_at": "2011-11-02 10:41:05",
            "reminded_at": "2011-10-18 08:27:17",
            "postalcode": "1041",
            "ward": 4,
            "is_fixed": true,
            "address": "Rue d'Arlon, 107",
            "desc": ""
        }
    },
    {
        "pk": 11,
        "model": "mainapp.report",
        "fields": {
            "category": 16,
            "is_hate": false,
            "sent_at": "2011-10-18 07:11:51",
            "is_confirmed": true,
            "title": "Poubelle pleine de crottes de chien",
            "photo": "",
            "created_at": "2011-10-18 07:00:01",
            "point": "POINT (150336.1093750000000000 170869.3593750000000000)",
            "updated_at": "2011-10-18 07:00:01",
            "email_sent_to": "jsanchezpandoF@cirb.irisnet.be",
            "author": "Jonathan",
            "fixed_at": null,
            "reminded_at": "2011-10-18 07:00:01",
            "postalcode": "1210",
            "ward": 14,
            "is_fixed": false,
            "address": "Rue Hydraulique, 49",
            "desc": "promeneurs de chiens dans les bois \u00e0 c\u00f4t\u00e9 de Patricia Ave ramasser leurs crottes de chien, mais souvent les laisser dans la poubelle \u00e0 l'entr\u00e9e. Cela a \u00e9t\u00e9 compl\u00e8te et non per\u00e7us depuis plusieurs semaines. Je sais que la ville ne recueille pas les excr\u00e9ments de chien, mais cela reste o\u00f9 il est un probl\u00e8me aussi."
        }
    },
    {
        "pk": 1,
        "model": "mainapp.reportupdate",
        "fields": {
            "confirm_token": "3abde3503b858849d1af53cab4c58d9d",
            "is_confirmed": true,
            "author": "Jonathan",
            "created_at": "2011-10-18 06:58:37",
            "first_update": true,
            "phone": "",
            "report": 1,
            "is_fixed": false,
            "email": "jsanchezpando@cirb.irisnet.be",
            "desc": ""
        }
    },
    {
        "pk": 2,
        "model": "mainapp.reportupdate",
        "fields": {
            "confirm_token": "eb93a53a734d9819898289440fe3abf6",
            "is_confirmed": true,
            "author": "Jonathan",
            "created_at": "2011-10-18 07:00:01",
            "first_update": true,
            "phone": "",
            "report": 2,
            "is_fixed": false,
            "email": "jsanchezpando@cirb.irisnet.be",
            "desc": ""
        }
    },
    {
        "pk": 3,
        "model": "mainapp.reportupdate",
        "fields": {
            "confirm_token": "cb99a6365b81e3a3c9ae636e59f9ae35",
            "is_confirmed": true,
            "author": "Jonathan",
            "created_at": "2011-10-18 07:01:58",
            "first_update": true,
            "phone": "",
            "report": 3,
            "is_fixed": false,
            "email": "jsanchezpando@cirb.irisnet.be",
            "desc": ""
        }
    },
    {
        "pk": 4,
        "model": "mainapp.reportupdate",
        "fields": {
            "confirm_token": "d70d48d99cb85790e5df41530675532c",
            "is_confirmed": true,
            "author": "Jonathan",
            "created_at": "2011-10-18 07:03:21",
            "first_update": true,
            "phone": "",
            "report": 4,
            "is_fixed": false,
            "email": "jsanchezpando@cirb.irisnet.be",
            "desc": ""
        }
    },
    {
        "pk": 5,
        "model": "mainapp.reportupdate",
        "fields": {
            "confirm_token": "d526825db9fb39de3f45eec2c2c015cb",
            "is_confirmed": true,
            "author": "Jonathan",
            "created_at": "2011-10-18 08:07:33",
            "first_update": true,
            "phone": "",
            "report": 5,
            "is_fixed": false,
            "email": "jsanchezpando@cirb.irisnet.be",
            "desc": ""
        }
    },
    {
        "pk": 6,
        "model": "mainapp.reportupdate",
        "fields": {
            "confirm_token": "b8f4517d542bac90b83ee9955c723aea",
            "is_confirmed": true,
            "author": "Jonathan",
            "created_at": "2011-10-18 08:27:17",
            "first_update": true,
            "phone": "",
            "report": 6,
            "is_fixed": false,
            "email": "jsanchezpando@cirb.irisnet.be",
            "desc": ""
        }
    },
    {
        "pk": 7,
        "model": "mainapp.reportupdate",
        "fields": {
            "confirm_token": "08eefe47691cd5b6a970661f21768b49",
            "is_confirmed": true,
            "author": "Jonathan",
            "created_at": "2011-10-18 08:46:22",
            "first_update": true,
            "phone": "",
            "report": 7,
            "is_fixed": false,
            "email": "jsanchezpando@cirb.irisnet.be",
            "desc": ""
        }
    },
    {
        "pk": 8,
        "model": "mainapp.reportupdate",
        "fields": {
            "confirm_token": "2a3ff60fdf5d55479544eb4e909f2330",
            "is_confirmed": true,
            "author": "Jonathan",
            "created_at": "2011-10-18 09:01:40",
            "first_update": true,
            "phone": "",
            "report": 8,
            "is_fixed": false,
            "email": "jsanchezpando@cirb.irisnet.be",
            "desc": ""
        }
    },
    {
        "pk": 9,
        "model": "mainapp.reportupdate",
        "fields": {
            "confirm_token": "c562672e34cc568262e482bd4a46cb12",
            "is_confirmed": true,
            "author": "Jonathan",
            "created_at": "2011-10-19 02:58:40",
            "first_update": true,
            "phone": "",
            "report": 9,
            "is_fixed": false,
            "email": "jsanchezpando@cirb.irisnet.be",
            "desc": ""
        }
    },
    {
        "pk": 10,
        "model": "mainapp.reportupdate",
        "fields": {
            "confirm_token": "5889fa03e82af7a0106627693b6aa717",
            "is_confirmed": true,
            "author": "Jonathan",
            "created_at": "2011-10-19 08:55:24",
            "first_update": false,
            "phone": "",
            "report": 10,
            "is_fixed": false,
            "email": "jsanchezpando@cirb.irisnet.be",
            "desc": "hello"
        }
    },
    {
        "pk": 11,
        "model": "mainapp.reportupdate",
        "fields": {
            "confirm_token": "801921e15fc31040878df85fcaa026e6",
            "is_confirmed": true,
            "author": "Jonathan",
            "created_at": "2011-10-19 09:01:38",
            "first_update": false,
            "phone": "",
            "report": 11,
            "is_fixed": false,
            "email": "jsanchezpando@cirb.irisnet.be",
            "desc": "Hello world"
        }
    },
    {
        "pk": 13,
        "model": "mainapp.reportupdate",
        "fields": {
            "confirm_token": "cbf96ed40b47dc24fbd3c18911008386",
            "is_confirmed": false,
            "author": "Auqui\u00e8re Eric",
            "created_at": "2011-10-21 03:22:58",
            "first_update": false,
            "phone": "",
            "report": 1,
            "is_fixed": false,
            "email": "eauquiere@cirb.irsnet.be",
            "desc": "Le tag a \u00e9t\u00e9 nettoy\u00e9 et remplac\u00e9 par une affiche du site portail r\u00e9gional"
        }
    },
    {
        "pk": 14,
        "model": "mainapp.reportupdate",
        "fields": {
            "confirm_token": "d4843c2886531e617703d29ead7f7a92",
            "is_confirmed": true,
            "author": "Auqui\u00e8re Eric",
            "created_at": "2011-10-21 03:31:01",
            "first_update": true,
            "phone": "",
            "report": 11,
            "is_fixed": false,
            "email": "eauquiere@cirb.irisnet.be",
            "desc": "Il n'y a pas d'enseigne au CIRB"
        }
    },
    {
        "pk": 15,
        "model": "mainapp.reportupdate",
        "fields": {
            "confirm_token": "5899566ca9db113f4be5715d6b68d412",
            "is_confirmed": true,
            "author": "Auqui\u00e8re Eric",
            "created_at": "2011-10-21 04:26:47",
            "first_update": true,
            "phone": "0498/4888888",
            "report": 12,
            "is_fixed": false,
            "email": "eauquiere@cirb.irisnet.be",
            "desc": "Grafiti sur la fesse gauche"
        }
    },
    {
        "pk": 18,
        "model": "mainapp.reportupdate",
        "fields": {
            "confirm_token": "1fc8bf0c41f7776b8614f5c520cb5d5f",
            "is_confirmed": false,
            "author": "Jonathan",
            "created_at": "2011-10-26 07:11:22",
            "first_update": false,
            "phone": "",
            "report": 8,
            "is_fixed": false,
            "email": "jsanchezpando@cirb.irisnet.be",
            "desc": "sgsdg"
        }
    },
    {
        "pk": 19,
        "model": "mainapp.reportupdate",
        "fields": {
            "confirm_token": "61f241aa8dd2d6b8dbf8e52f5c650f7f",
            "is_confirmed": false,
            "author": "Jonathan",
            "created_at": "2011-10-26 07:16:16",
            "first_update": false,
            "phone": "",
            "report": 8,
            "is_fixed": false,
            "email": "jsanchezpando@cirb.irisnet.be",
            "desc": "sgsdg"
        }
    },
    {
        "pk": 20,
        "model": "mainapp.reportupdate",
        "fields": {
            "confirm_token": "d6273a8686615e623d4d825960e8b51c",
            "is_confirmed": false,
            "author": "Jonathan",
            "created_at": "2011-10-26 07:47:22",
            "first_update": false,
            "phone": "",
            "report": 8,
            "is_fixed": false,
            "email": "jsanchezpando@cirb.irisnet.be",
            "desc": "gndgnfgn"
        }
    },
    {
        "pk": 21,
        "model": "mainapp.reportupdate",
        "fields": {
            "confirm_token": "354d886f910a20f67e20c1341513d3d2",
            "is_confirmed": false,
            "author": "Jonathan",
            "created_at": "2011-10-26 07:49:24",
            "first_update": false,
            "phone": "",
            "report": 8,
            "is_fixed": false,
            "email": "jsanchezpando@cirb.irisnet.be",
            "desc": "gndgnfgn"
        }
    },
    {
        "pk": 22,
        "model": "mainapp.reportupdate",
        "fields": {
            "confirm_token": "c10f01680113070e8ce471bca1ca3b98",
            "is_confirmed": false,
            "author": "Jonathan",
            "created_at": "2011-10-26 07:52:30",
            "first_update": false,
            "phone": "",
            "report": 8,
            "is_fixed": false,
            "email": "jsanchezpando@cirb.irisnet.be",
            "desc": "gndgnfgn"
        }
    },
    {
        "pk": 23,
        "model": "mainapp.reportupdate",
        "fields": {
            "confirm_token": "c2ea898ad3ff091a08fd0d06f2a1ec38",
            "is_confirmed": false,
            "author": "Jonathan",
            "created_at": "2011-10-26 07:54:38",
            "first_update": false,
            "phone": "",
            "report": 8,
            "is_fixed": false,
            "email": "jsanchezpando@cirb.irisnet.be",
            "desc": "gndgnfgn"
        }
    },
    {
        "pk": 24,
        "model": "mainapp.reportupdate",
        "fields": {
            "confirm_token": "a26655bf79874570f5cc04b6437dd88e",
            "is_confirmed": false,
            "author": "Jonathan",
            "created_at": "2011-10-26 07:55:37",
            "first_update": false,
            "phone": "",
            "report": 8,
            "is_fixed": false,
            "email": "jsanchezpando@cirb.irisnet.be",
            "desc": "gndgnfgn"
        }
    },
    {
        "pk": 25,
        "model": "mainapp.reportupdate",
        "fields": {
            "confirm_token": "0a05d6a037222026f208db392f8a7593",
            "is_confirmed": false,
            "author": "Jonathan",
            "created_at": "2011-10-26 07:57:01",
            "first_update": false,
            "phone": "",
            "report": 8,
            "is_fixed": false,
            "email": "jsanchezpando@cirb.irisnet.be",
            "desc": "gndgnfgn"
        }
    },
    {
        "pk": 26,
        "model": "mainapp.reportupdate",
        "fields": {
            "confirm_token": "57388a27a134974c2130f4bd14ec9e26",
            "is_confirmed": false,
            "author": "Jonathan",
            "created_at": "2011-10-26 08:01:39",
            "first_update": false,
            "phone": "",
            "report": 8,
            "is_fixed": false,
            "email": "jsanchezpando@cirb.irisnet.be",
            "desc": "gndgnfgn"
        }
    },
    {
        "pk": 27,
        "model": "mainapp.reportupdate",
        "fields": {
            "confirm_token": "fc814c9465a4cf91958e5d16a7a34a5b",
            "is_confirmed": false,
            "author": "Jonathan",
            "created_at": "2011-10-26 08:02:36",
            "first_update": false,
            "phone": "",
            "report": 8,
            "is_fixed": false,
            "email": "jsanchezpando@cirb.irisnet.be",
            "desc": "gndgnfgn"
        }
    },
    {
        "pk": 28,
        "model": "mainapp.reportupdate",
        "fields": {
            "confirm_token": "6cca403d19b4ffbe86fe411788b70b0b",
            "is_confirmed": false,
            "author": "Jonathan",
            "created_at": "2011-10-26 08:07:20",
            "first_update": false,
            "phone": "",
            "report": 8,
            "is_fixed": false,
            "email": "jsanchezpando@cirb.irisnet.be",
            "desc": "zefzef"
        }
    },
    {
        "pk": 29,
        "model": "mainapp.reportupdate",
        "fields": {
            "confirm_token": "219088e49df9d2c6c626fae2aad8a41b",
            "is_confirmed": false,
            "author": "Jonathan",
            "created_at": "2011-10-26 08:10:25",
            "first_update": false,
            "phone": "",
            "report": 8,
            "is_fixed": false,
            "email": "jsanchezpando@cirb.irisnet.be",
            "desc": "zefzef"
        }
    },
    {
        "pk": 30,
        "model": "mainapp.reportupdate",
        "fields": {
            "confirm_token": "c210f231473bd0d357d0c6e1cded5c6a",
            "is_confirmed": false,
            "author": "Jonathan",
            "created_at": "2011-10-26 08:13:41",
            "first_update": false,
            "phone": "",
            "report": 8,
            "is_fixed": false,
            "email": "jsanchezpando@cirb.irisnet.be",
            "desc": "zefzef"
        }
    },
    {
        "pk": 31,
        "model": "mainapp.reportupdate",
        "fields": {
            "confirm_token": "29786009b4cf7773ffe684a5ef0a6d2e",
            "is_confirmed": false,
            "author": "Jonathan",
            "created_at": "2011-10-26 08:14:05",
            "first_update": false,
            "phone": "",
            "report": 8,
            "is_fixed": false,
            "email": "jsanchezpando@cirb.irisnet.be",
            "desc": "zefzef"
        }
    },
    {
        "pk": 32,
        "model": "mainapp.reportupdate",
        "fields": {
            "confirm_token": "318cd374c915858802f62928596f0818",
            "is_confirmed": false,
            "author": "Jonathan",
            "created_at": "2011-10-26 08:17:57",
            "first_update": false,
            "phone": "",
            "report": 8,
            "is_fixed": false,
            "email": "jsanchezpando@cirb.irisnet.be",
            "desc": "zefzef"
        }
    },
    {
        "pk": 33,
        "model": "mainapp.reportupdate",
        "fields": {
            "confirm_token": "b72cf88b2c9eeb096b3506efcdd10bbc",
            "is_confirmed": false,
            "author": "Jonathan",
            "created_at": "2011-10-26 08:18:38",
            "first_update": false,
            "phone": "",
            "report": 8,
            "is_fixed": false,
            "email": "jsanchezpando@cirb.irisnet.be",
            "desc": "zefzef"
        }
    },
    {
        "pk": 34,
        "model": "mainapp.reportupdate",
        "fields": {
            "confirm_token": "736f4cb438785a606c7e40f6cad12187",
            "is_confirmed": false,
            "author": "Jonathan",
            "created_at": "2011-10-26 08:27:40",
            "first_update": false,
            "phone": "",
            "report": 8,
            "is_fixed": false,
            "email": "jsanchezpando@cirb.irisnet.be",
            "desc": "zefzef"
        }
    },
    {
        "pk": 35,
        "model": "mainapp.reportupdate",
        "fields": {
            "confirm_token": "947166376b3832a03db697547aa7ba3a",
            "is_confirmed": false,
            "author": "Jonathan",
            "created_at": "2011-10-26 08:39:44",
            "first_update": false,
            "phone": "",
            "report": 8,
            "is_fixed": false,
            "email": "jsanchezpando@cirb.irisnet.be",
            "desc": "zefzef"
        }
    },
    {
        "pk": 36,
        "model": "mainapp.reportupdate",
        "fields": {
            "confirm_token": "92b5c6089b9c26ecaa4d2e31c2f60858",
            "is_confirmed": false,
            "author": "Jonathan",
            "created_at": "2011-10-26 08:40:21",
            "first_update": false,
            "phone": "",
            "report": 8,
            "is_fixed": false,
            "email": "jsanchezpando@cirb.irisnet.be",
            "desc": "zefzef"
        }
    },
    {
        "pk": 37,
        "model": "mainapp.reportupdate",
        "fields": {
            "confirm_token": "689d804031ab41e0bbd685bbad2bfa6c",
            "is_confirmed": false,
            "author": "Jonathan",
            "created_at": "2011-10-26 08:40:42",
            "first_update": false,
            "phone": "",
            "report": 8,
            "is_fixed": false,
            "email": "jsanchezpando@cirb.irisnet.be",
            "desc": "zefzef"
        }
    },
    {
        "pk": 38,
        "model": "mainapp.reportupdate",
        "fields": {
            "confirm_token": "381877b241280a97ec1974329f500d64",
            "is_confirmed": false,
            "author": "Jonathan",
            "created_at": "2011-10-26 08:40:48",
            "first_update": false,
            "phone": "",
            "report": 8,
            "is_fixed": false,
            "email": "jsanchezpando@cirb.irisnet.be",
            "desc": "zefzef"
        }
    },
    {
        "pk": 39,
        "model": "mainapp.reportupdate",
        "fields": {
            "confirm_token": "b87d0761269933b52a3d6e2f3dd3782c",
            "is_confirmed": false,
            "author": "Jonathan",
            "created_at": "2011-10-26 08:47:59",
            "first_update": false,
            "phone": "",
            "report": 8,
            "is_fixed": false,
            "email": "jsanchezpando@cirb.irisnet.be",
            "desc": "fsdf"
        }
    },
    {
        "pk": 40,
        "model": "mainapp.reportupdate",
        "fields": {
            "confirm_token": "75a6415304a133ce93a53765b8b64f1a",
            "is_confirmed": false,
            "author": "Jonathan",
            "created_at": "2011-10-26 08:48:37",
            "first_update": false,
            "phone": "",
            "report": 8,
            "is_fixed": false,
            "email": "jsanchezpando@cirb.irisnet.be",
            "desc": "fsdf"
        }
    },
    {
        "pk": 41,
        "model": "mainapp.reportupdate",
        "fields": {
            "confirm_token": "eb30c92f9141087877cb4aa655a63b28",
            "is_confirmed": false,
            "author": "Jonathan",
            "created_at": "2011-10-26 08:49:49",
            "first_update": false,
            "phone": "",
            "report": 8,
            "is_fixed": false,
            "email": "jsanchezpando@cirb.irisnet.be",
            "desc": "fsdf"
        }
    },
    {
        "pk": 42,
        "model": "mainapp.reportupdate",
        "fields": {
            "confirm_token": "b2c7caa388565de315a97b8f969d09f2",
            "is_confirmed": false,
            "author": "Jonathan",
            "created_at": "2011-10-26 08:50:32",
            "first_update": false,
            "phone": "",
            "report": 8,
            "is_fixed": false,
            "email": "jsanchezpando@cirb.irisnet.be",
            "desc": "fsdf"
        }
    },
    {
        "pk": 43,
        "model": "mainapp.reportupdate",
        "fields": {
            "confirm_token": "276c64f7b9e94725d0fe09875cdd0f16",
            "is_confirmed": false,
            "author": "Jonathan",
            "created_at": "2011-10-26 08:50:42",
            "first_update": false,
            "phone": "",
            "report": 8,
            "is_fixed": false,
            "email": "jsanchezpando@cirb.irisnet.be",
            "desc": "fsdf"
        }
    },
    {
        "pk": 44,
        "model": "mainapp.reportupdate",
        "fields": {
            "confirm_token": "a4b19a7b24dd290173a137667f14ab43",
            "is_confirmed": false,
            "author": "Jonathan",
            "created_at": "2011-10-26 08:52:07",
            "first_update": false,
            "phone": "",
            "report": 8,
            "is_fixed": false,
            "email": "jsanchezpando@cirb.irisnet.be",
            "desc": "fsdf"
        }
    },
    {
        "pk": 45,
        "model": "mainapp.reportupdate",
        "fields": {
            "confirm_token": "283782e2b09c3a1b4fdcb30a5b38fb40",
            "is_confirmed": false,
            "author": "Jonathan",
            "created_at": "2011-10-26 09:14:46",
            "first_update": false,
            "phone": "",
            "report": 10,
            "is_fixed": false,
            "email": "jsanchezpando@cirb.irisnet.be",
            "desc": "jhghj"
        }
    },
    {
        "pk": 83,
        "model": "mainapp.reportupdate",
        "fields": {
            "confirm_token": "fdf3cb94a53a4a74e2b475f6363b5a85",
            "is_confirmed": true,
            "author": "Jonathan",
            "created_at": "2011-11-02 10:52:08",
            "first_update": false,
            "phone": "",
            "report": 8,
            "is_fixed": true,
            "email": "jsanchezpando@cirb.irisnet.be",
            "desc": "Le grafity a \u00e9t\u00e9 netay\u00e9"
        }
    },
    {
        "pk": 52,
        "model": "mainapp.reportupdate",
        "fields": {
            "confirm_token": "bb253b5c713c60e117bc2e0275382f90",
            "is_confirmed": false,
            "author": "Jonathan",
            "created_at": "2011-10-27 08:38:09",
            "first_update": false,
            "phone": "",
            "report": 10,
            "is_fixed": false,
            "email": "jsanchezpando@cirb.irisnet.be",
            "desc": "fzsgsdfg"
        }
    },
    {
        "pk": 53,
        "model": "mainapp.reportupdate",
        "fields": {
            "confirm_token": "2b85b25b7ef6c668bc0a732b5937d752",
            "is_confirmed": false,
            "author": "Jonathan",
            "created_at": "2011-10-27 08:40:56",
            "first_update": false,
            "phone": "",
            "report": 10,
            "is_fixed": false,
            "email": "jsanchezpando@cirb.irisnet.be",
            "desc": "fzsgsdfg"
        }
    },
    {
        "pk": 54,
        "model": "mainapp.reportupdate",
        "fields": {
            "confirm_token": "66afa8ac11480ff9c51994fc3ed11a20",
            "is_confirmed": false,
            "author": "Jonathan",
            "created_at": "2011-10-27 08:46:22",
            "first_update": false,
            "phone": "",
            "report": 10,
            "is_fixed": false,
            "email": "jsanchezpando@cirb.irisnet.be",
            "desc": "fzsgsdfg"
        }
    },
    {
        "pk": 55,
        "model": "mainapp.reportupdate",
        "fields": {
            "confirm_token": "0d47a667dbf995defd3fc932d5d27eee",
            "is_confirmed": false,
            "author": "Jonathan",
            "created_at": "2011-10-27 08:46:55",
            "first_update": false,
            "phone": "",
            "report": 10,
            "is_fixed": false,
            "email": "jsanchezpando@cirb.irisnet.be",
            "desc": "fzsgsdfg"
        }
    },
    {
        "pk": 81,
        "model": "mainapp.reportupdate",
        "fields": {
            "confirm_token": "960f98892601d21a39c597812121b8fe",
            "is_confirmed": true,
            "author": "Jonathan",
            "created_at": "2011-11-02 10:41:05",
            "first_update": false,
            "phone": "",
            "report": 6,
            "is_fixed": true,
            "email": "jsanchezpando@cirb.irisnet.be",
            "desc": "Il a \u00e9t\u00e9 retir\u00e9"
        }
    },
    {
        "pk": 82,
        "model": "mainapp.reportupdate",
        "fields": {
            "confirm_token": "1a3d22c544435acbe4696e7143e068c3",
            "is_confirmed": false,
            "author": "Jonathan",
            "created_at": "2011-11-02 10:52:02",
            "first_update": false,
            "phone": "",
            "report": 8,
            "is_fixed": false,
            "email": "jsanchezpando@cirb.irisnet.be",
            "desc": "Le grafity a \u00e9t\u00e9 netay\u00e9"
        }
    }
]
